{"type": "FeatureCollection", "features": [ {"type":"Feature","properties": { "id": "1", "Title":"Belle statue!!!", "description": "Wow elle est trop belle cette statue", "name": "Sculpture", "period": "Antiquité", "icon":"theatre", "color": "antiquite2.jpg" }, "geometry": { "type": "Point", "coordinates": [4.827420, 45.779557 ] } },{"type":"Feature","properties": { "id": "2", "Title":"Belle statue dfdfd dfsfjsofr jsf smlfjsdfsflsd kldfkslfksdl fksf kslfksdlf klsdfmk lsdf lsf slfsmlfsdd dfdsfsd sfsdf dfsdf df sfsd dsf !!! dfksfj dfdslodf ksdfds ksdfsüf sdkf spdfsfk sfsf üsf küsf sf üpsf südf sfs kü", "description": "Wow elle est trop belle cette statue", "name": "Sculpture", "period": "Antiquité", "icon": "theatre", "color":"antiquite2.jpg" }, "geometry": { "type": "Point", "coordinates": [4.787420, 47.779557 ] } } ] }